records/__init__.py
records/extras.py
records/field.py
records/fillers/__init__.py
records/fillers/builtin_fillers/__init__.py
records/fillers/builtin_fillers/recurse.py
records/fillers/builtin_fillers/repo.py
records/fillers/builtin_fillers/std_fillers.py
records/fillers/builtin_fillers/typing_fillers.py
records/fillers/builtin_validators.py
records/fillers/coercers.py
records/fillers/filler.py
records/fillers/get_filler.py
records/fillers/util.py
records/fillers/validators.py
records/record.py
records/select.py
records/tags.py
records/utils/__init__.py
records/utils/decorators.py
records/utils/typing_compatible.py
recordclasses-0.0.1.dist-info/LICENSE
recordclasses-0.0.1.dist-info/WHEEL
recordclasses-0.0.1.dist-info/METADATA
recordclasses-0.0.1.dist-info/RECORD
