Metadata-Version: 2.1
Name: recordclasses
Version: 0.0.1
Summary: Record Classes
Home-page: https://github.com/bentheiii/Records
License: MIT
Author: Ben Avrahami
Requires-Python: >=3.7,<4.0
Classifier: License :: OSI Approved :: MIT License
Classifier: Programming Language :: Python :: 3
Classifier: Programming Language :: Python :: 3.7
Classifier: Programming Language :: Python :: 3.8
Project-URL: Repository, https://github.com/bentheiii/Records
